<?xml version="1.0" encoding="utf-8"?>                                                                                                                                                                                                                         
<edmx:Edmx Version="1.0" xmlns:edmx="http://schemas.microsoft.com/ado/2007/06/edmx" xmlns:m="http://schemas.microsoft.com/ado/2007/08/dataservices/metadata" xmlns:sap="http://www.sap.com/Protocols/SAPData">                                                 
    <edmx:Reference Uri="https://fiori-dev.3coracoes.com.br:443/sap/opu/odata/IWFND/CATALOGSERVICE;v=2/Vocabularies(TechnicalName='%2FIWBEP%2FVOC_COMMON',Version='0001',SAP__Origin='')/$value" xmlns:edmx="http://docs.oasis-open.org/odata/ns/edmx">        
        <edmx:Include Namespace="com.sap.vocabularies.Common.v1" Alias="Common"/>                                                                                                                                                                              
    </edmx:Reference>                                                                                                                                                                                                                                          
    <edmx:Reference Uri="https://fiori-dev.3coracoes.com.br:443/sap/opu/odata/IWFND/CATALOGSERVICE;v=2/Vocabularies(TechnicalName='%2FIWBEP%2FVOC_CAPABILITIES',Version='0001',SAP__Origin='')/$value" xmlns:edmx="http://docs.oasis-open.org/odata/ns/edmx">  
        <edmx:Include Namespace="Org.OData.Capabilities.V1" Alias="Capabilities"/>                                                                                                                                                                             
    </edmx:Reference>                                                                                                                                                                                                                                          
    <edmx:Reference Uri="https://fiori-dev.3coracoes.com.br:443/sap/opu/odata/IWFND/CATALOGSERVICE;v=2/Vocabularies(TechnicalName='%2FIWBEP%2FVOC_COMMUNICATION',Version='0001',SAP__Origin='')/$value" xmlns:edmx="http://docs.oasis-open.org/odata/ns/edmx"> 
        <edmx:Include Namespace="com.sap.vocabularies.Communication.v1" Alias="Communication"/>                                                                                                                                                                
    </edmx:Reference>                                                                                                                                                                                                                                          
    <edmx:Reference Uri="https://fiori-dev.3coracoes.com.br:443/sap/opu/odata/IWFND/CATALOGSERVICE;v=2/Vocabularies(TechnicalName='%2FIWBEP%2FVOC_AGGREGATION',Version='0001',SAP__Origin='')/$value" xmlns:edmx="http://docs.oasis-open.org/odata/ns/edmx">   
        <edmx:Include Namespace="Org.OData.Aggregation.V1" Alias="Aggregation"/>                                                                                                                                                                               
    </edmx:Reference>                                                                                                                                                                                                                                          
    <edmx:Reference Uri="https://fiori-dev.3coracoes.com.br:443/sap/opu/odata/IWFND/CATALOGSERVICE;v=2/Vocabularies(TechnicalName='%2FIWBEP%2FVOC_PERSONALDATA',Version='0001',SAP__Origin='')/$value" xmlns:edmx="http://docs.oasis-open.org/odata/ns/edmx">  
        <edmx:Include Namespace="com.sap.vocabularies.PersonalData.v1" Alias="PersonalData"/>                                                                                                                                                                  
    </edmx:Reference>                                                                                                                                                                                                                                          
    <edmx:Reference Uri="https://fiori-dev.3coracoes.com.br:443/sap/opu/odata/IWFND/CATALOGSERVICE;v=2/Vocabularies(TechnicalName='%2FIWBEP%2FVOC_VALIDATION',Version='0001',SAP__Origin='')/$value" xmlns:edmx="http://docs.oasis-open.org/odata/ns/edmx">    
        <edmx:Include Namespace="Org.OData.Validation.V1" Alias="Validation"/>                                                                                                                                                                                 
    </edmx:Reference>                                                                                                                                                                                                                                          
    <edmx:Reference Uri="https://fiori-dev.3coracoes.com.br:443/sap/opu/odata/IWFND/CATALOGSERVICE;v=2/Vocabularies(TechnicalName='%2FIWBEP%2FVOC_ANALYTICS',Version='0001',SAP__Origin='')/$value" xmlns:edmx="http://docs.oasis-open.org/odata/ns/edmx">     
        <edmx:Include Namespace="com.sap.vocabularies.Analytics.v1" Alias="Analytics"/>                                                                                                                                                                        
    </edmx:Reference>                                                                                                                                                                                                                                          
    <edmx:Reference Uri="https://fiori-dev.3coracoes.com.br:443/sap/opu/odata/IWFND/CATALOGSERVICE;v=2/Vocabularies(TechnicalName='%2FIWBEP%2FVOC_MEASURES',Version='0001',SAP__Origin='')/$value" xmlns:edmx="http://docs.oasis-open.org/odata/ns/edmx">      
        <edmx:Include Namespace="Org.OData.Measures.V1" Alias="Measures"/>                                                                                                                                                                                     
    </edmx:Reference>                                                                                                                                                                                                                                          
    <edmx:Reference Uri="https://fiori-dev.3coracoes.com.br:443/sap/opu/odata/IWFND/CATALOGSERVICE;v=2/Vocabularies(TechnicalName='%2FIWBEP%2FVOC_UI',Version='0001',SAP__Origin='')/$value" xmlns:edmx="http://docs.oasis-open.org/odata/ns/edmx">            
        <edmx:Include Namespace="com.sap.vocabularies.UI.v1" Alias="UI"/>                                                                                                                                                                                      
    </edmx:Reference>                                                                                                                                                                                                                                          
    <edmx:DataServices m:DataServiceVersion="2.0">                                                                                                                                                                                                             
        <Schema Namespace="cds_zui_mm_expedinsum_espc_subcont" xml:lang="pt" sap:schema-version="1" xmlns="http://schemas.microsoft.com/ado/2008/09/edm">                                                                                                      
            <EntityType Name="App_ExpedEspSubType" sap:label="Exped.Insumos-Especial - Subcontratação" sap:content-version="1">                                                                                                                                
                <Key>                                                                                                                                                                                                                                          
                    <PropertyRef Name="Rsnum"/>                                                                                                                                                                                                                
                    <PropertyRef Name="Rspos"/>                                                                                                                                                                                                                
                </Key>                                                                                                                                                                                                                                         
                <Property Name="Rsnum" Type="Edm.String" Nullable="false" MaxLength="10" sap:display-format="NonNegative" sap:label="Reserva" sap:quickinfo="Nº reserva / necessidades dependentes"/>                                                          
                <Property Name="Rspos" Type="Edm.String" Nullable="false" MaxLength="4" sap:display-format="NonNegative" sap:label="Item" sap:quickinfo="Nº item da reserva / das necessidades dependentes"/>                                                  
                <Property Name="Bdart" Type="Edm.String" MaxLength="2" sap:display-format="UpperCase" sap:label="Tipo de necessidade"/>                                                                                                                        
                <Property Name="Werks" Type="Edm.String" MaxLength="4" sap:display-format="UpperCase" sap:label="Centro"/>                                                                                                                                     
                <Property Name="Matnr" Type="Edm.String" MaxLength="18" sap:display-format="UpperCase" sap:label="Material" sap:quickinfo="Nº do material"/>                                                                                                   
                <Property Name="Ebeln" Type="Edm.String" MaxLength="10" sap:display-format="UpperCase" sap:label="Documento de compras" sap:quickinfo="Nº do documento de compras"/>                                                                           
                <Property Name="Ebelp" Type="Edm.String" MaxLength="5" sap:display-format="NonNegative" sap:label="Item" sap:quickinfo="Nº item do documento de compra"/>                                                                                      
                <Property Name="Bdter" Type="Edm.DateTime" Precision="0" sap:display-format="Date" sap:label="Data da necessidade" sap:quickinfo="Data necessidade do componente"/>                                                                            
                <Property Name="Lifnr" Type="Edm.String" MaxLength="10" sap:display-format="UpperCase" sap:label="Fornecedor" sap:quickinfo="Nº conta do fornecedor"/>                                                                                         
                <Property Name="Menge" Type="Edm.Decimal" Precision="13" Scale="3" sap:unit="Meins" sap:label="Qtd.necessária" sap:quickinfo="Quantidade necessária"/>                                                                                         
                <Property Name="Meins" Type="Edm.String" MaxLength="3" sap:label="Unid.medida básica" sap:quickinfo="Unidade de medida básica" sap:semantics="unit-of-measure"/>                                                                               
                <Property Name="DescFornec" Type="Edm.String" MaxLength="35" sap:label="Nome" sap:quickinfo="Nome 1"/>                                                                                                                                         
                <Property Name="XML_Transp" Type="Edm.String" MaxLength="44" sap:label="XML para Expedição" sap:quickinfo="Chave de acesso de 44 caracteres"/>                                                                                                 
                <Property Name="MarkCriticality" Type="Edm.Byte"/>                                                                                                                                                                                             
                <Property Name="Status" Type="Edm.String" MaxLength="14"/>                                                                                                                                                                                     
                <Property Name="StatusCriticality" Type="Edm.Byte"/>                                                                                                                                                                                           
                <Property Name="Vbeln" Type="Edm.String" MaxLength="10" sap:display-format="UpperCase" sap:label="Remessa"/>                                                                                                                                   
                <Property Name="XmlEntrad" Type="Edm.String" MaxLength="70" sap:label="XML Entrada do Insumo" sap:quickinfo="Local incoterms 2"/>                                                                                                              
                <Property Name="Mblnr" Type="Edm.String" MaxLength="10" sap:display-format="UpperCase" sap:label="Doc.material" sap:quickinfo="Número do documento do material"/>                                                                              
                <Property Name="Docnum" Type="Edm.String" MaxLength="10" sap:display-format="NonNegative" sap:label="Nº documento"/>                                                                                                                           
                <Property Name="Pstdat" Type="Edm.DateTime" Precision="0" sap:display-format="Date" sap:label="Data de lançamento"/>                                                                                                                           
                <Property Name="Nfenum" Type="Edm.String" MaxLength="9" sap:display-format="UpperCase" sap:label="Nº da NF-e" sap:quickinfo="Número de nota fiscal eletrônica"/>                                                                               
                <Property Name="Quantidade" Type="Edm.Decimal" Precision="14" Scale="3"/>                                                                                                                                                                      
                <Property Name="DescMat" Type="Edm.String" MaxLength="40" sap:label="Texto breve material" sap:quickinfo="Texto breve de material" sap:creatable="false" sap:updatable="false"/>                                                               
                <Property Name="DesCentro" Type="Edm.String" MaxLength="30" sap:label="Nome 1" sap:quickinfo="Nome" sap:creatable="false" sap:updatable="false"/>                                                                                              
                <Property Name="Transptdr" Type="Edm.String" MaxLength="1" sap:label="Transportadora"/>                                                                                                                                                        
                <Property Name="Incoterms1" Type="Edm.String" MaxLength="1" sap:label="Incoterms 1"/>                                                                                                                                                          
                <Property Name="Incoterms2" Type="Edm.String" MaxLength="1" sap:label="Incoterms 2"/>                                                                                                                                                          
                <Property Name="TRAID" Type="Edm.String" MaxLength="1" sap:label="Placa"/>                                                                                                                                                                     
            </EntityType>                                                                                                                                                                                                                                      
            <ComplexType Name="DummyFunctionImportResult">                                                                                                                                                                                                     
                <Property Name="IsInvalid" Type="Edm.Boolean" sap:label="Verdadeiro"/>                                                                                                                                                                         
            </ComplexType>                                                                                                                                                                                                                                     
            <EntityContainer Name="cds_zui_mm_expedinsum_espc_subcont_Entities" m:IsDefaultEntityContainer="true" sap:message-scope-supported="true" sap:supported-formats="atom json xlsx">                                                                   
                <EntitySet Name="App_ExpedEspSub" EntityType="cds_zui_mm_expedinsum_espc_subcont.App_ExpedEspSubType" sap:creatable="false" sap:updatable="false" sap:deletable="false" sap:content-version="1"/>                                              
                <FunctionImport Name="EstrnExped" ReturnType="cds_zui_mm_expedinsum_espc_subcont.DummyFunctionImportResult" m:HttpMethod="POST" sap:action-for="cds_zui_mm_expedinsum_espc_subcont.App_ExpedEspSubType">                                       
                    <Parameter Name="Rsnum" Type="Edm.String" Mode="In" MaxLength="10"/>                                                                                                                                                                       
                    <Parameter Name="Rspos" Type="Edm.String" Mode="In" MaxLength="4"/>                                                                                                                                                                        
                </FunctionImport>                                                                                                                                                                                                                              
                <FunctionImport Name="Expedicao" ReturnType="cds_zui_mm_expedinsum_espc_subcont.DummyFunctionImportResult" m:HttpMethod="POST" sap:action-for="cds_zui_mm_expedinsum_espc_subcont.App_ExpedEspSubType">                                        
                    <Parameter Name="Rsnum" Type="Edm.String" Mode="In" MaxLength="10"/>                                                                                                                                                                       
                    <Parameter Name="Rspos" Type="Edm.String" Mode="In" MaxLength="4"/>                                                                                                                                                                        
                    <Parameter Name="XML_Transp" Type="Edm.String" Mode="In" MaxLength="44" Nullable="true"/>                                                                                                                                                  
                    <Parameter Name="Transptdr" Type="Edm.String" Mode="In" MaxLength="10" Nullable="true"/>                                                                                                                                                   
                    <Parameter Name="Incoterms1" Type="Edm.String" Mode="In" MaxLength="3" Nullable="true"/>                                                                                                                                                   
                    <Parameter Name="Incoterms2" Type="Edm.String" Mode="In" MaxLength="28" Nullable="true"/>                                                                                                                                                  
                    <Parameter Name="TRAID" Type="Edm.String" Mode="In" MaxLength="20" Nullable="true"/>                                                                                                                                                       
                </FunctionImport>                                                                                                                                                                                                                              
                <FunctionImport Name="LimpMark" ReturnType="cds_zui_mm_expedinsum_espc_subcont.DummyFunctionImportResult" m:HttpMethod="POST" sap:action-for="cds_zui_mm_expedinsum_espc_subcont.App_ExpedEspSubType">                                         
                    <Parameter Name="Rsnum" Type="Edm.String" Mode="In" MaxLength="10"/>                                                                                                                                                                       
                    <Parameter Name="Rspos" Type="Edm.String" Mode="In" MaxLength="4"/>                                                                                                                                                                        
                </FunctionImport>                                                                                                                                                                                                                              
                <FunctionImport Name="MarkLine" ReturnType="cds_zui_mm_expedinsum_espc_subcont.DummyFunctionImportResult" m:HttpMethod="POST" sap:action-for="cds_zui_mm_expedinsum_espc_subcont.App_ExpedEspSubType">                                         
                    <Parameter Name="Rsnum" Type="Edm.String" Mode="In" MaxLength="10"/>                                                                                                                                                                       
                    <Parameter Name="Rspos" Type="Edm.String" Mode="In" MaxLength="4"/>                                                                                                                                                                        
                    <Parameter Name="XML_Transp" Type="Edm.String" Mode="In" MaxLength="44" Nullable="true"/>                                                                                                                                                  
                </FunctionImport>                                                                                                                                                                                                                              
            </EntityContainer>                                                                                                                                                                                                                                 
            <Annotations Target="cds_zui_mm_expedinsum_espc_subcont.cds_zui_mm_expedinsum_espc_subcont_Entities" xmlns="http://docs.oasis-open.org/odata/ns/edm">                                                                                              
                <Annotation Term="Common.ApplyMultiUnitBehaviorForSortingAndFiltering" Bool="true"/>                                                                                                                                                           
                <Annotation Term="Aggregation.ApplySupported">                                                                                                                                                                                                 
                    <Record>                                                                                                                                                                                                                                   
                        <PropertyValue Property="Transformations">                                                                                                                                                                                             
                            <Collection>                                                                                                                                                                                                                       
                                <String>aggregate</String>                                                                                                                                                                                                     
                                <String>groupby</String>                                                                                                                                                                                                       
                                <String>filter</String>                                                                                                                                                                                                        
                            </Collection>                                                                                                                                                                                                                      
                        </PropertyValue>                                                                                                                                                                                                                       
                        <PropertyValue Property="Rollup" EnumMember="None"/>                                                                                                                                                                                   
                    </Record>                                                                                                                                                                                                                                  
                </Annotation>                                                                                                                                                                                                                                  
            </Annotations>                                                                                                                                                                                                                                     
            <atom:link rel="self" href="https://fiori-dev.3coracoes.com.br:443/sap/opu/odata/sap/ZUI_O2_EXPED_ESPC_SUBCONT/$metadata" xmlns:atom="http://www.w3.org/2005/Atom"/>                                                                               
            <atom:link rel="latest-version" href="https://fiori-dev.3coracoes.com.br:443/sap/opu/odata/sap/ZUI_O2_EXPED_ESPC_SUBCONT/$metadata" xmlns:atom="http://www.w3.org/2005/Atom"/>                                                                     
        </Schema>                                                                                                                                                                                                                                              
    </edmx:DataServices>                                                                                                                                                                                                                                       
</edmx:Edmx>                                                                                                                                                                                                                                                   